deribit/__init__.py
deribit/__init__.pyi
deribit/_deribit.py
deribit/account/__init__.py
deribit/account/__init__.pyi
deribit/account/_account.py
deribit/account/get_account_summaries.py
deribit/account/get_account_summary.py
deribit/account/get_transaction_log.py
deribit/core/__init__.py
deribit/core/__init__.pyi
deribit/core/client.py
deribit/core/exc.py
deribit/core/util.py
deribit/core/validation.py
deribit/core/http/__init__.py
deribit/core/http/__init__.pyi
deribit/core/http/auth.py
deribit/core/http/client.py
deribit/core/ws/__init__.py
deribit/core/ws/__init__.pyi
deribit/core/ws/auth.py
deribit/core/ws/base.py
deribit/core/ws/client.py
deribit/core/ws/multiplex_streams_rpc.py
deribit/market_data/__init__.py
deribit/market_data/__init__.pyi
deribit/market_data/_market_data.py
deribit/market_data/get_contract_size.py
deribit/market_data/get_currencies.py
deribit/market_data/get_funding_rate_history.py
deribit/market_data/get_index_price.py
deribit/market_data/get_instrument.py
deribit/market_data/get_instruments.py
deribit/market_data/get_last_trades_by_instrument.py
deribit/market_data/get_order_book.py
deribit/market_data/get_tradingview_chart_data.py
deribit/market_data/ticker.py
deribit/sdk/__init__.py
deribit/sdk/__init__.pyi
deribit/sdk/_sdk.py
deribit/sdk/core/__init__.py
deribit/sdk/core/__init__.pyi
deribit/sdk/core/exc.py
deribit/sdk/core/mixin.py
deribit/sdk/core/naming.py
deribit/sdk/core/parsing.py
deribit/sdk/market/__init__.py
deribit/sdk/market/__init__.pyi
deribit/sdk/market/_market.py
deribit/sdk/market/market_data/__init__.py
deribit/sdk/market/market_data/__init__.pyi
deribit/sdk/market/market_data/_market_data.py
deribit/sdk/market/market_data/candles.py
deribit/sdk/market/market_data/depth.py
deribit/sdk/market/market_data/instrument_info.py
deribit/sdk/market/market_data/time.py
deribit/sdk/market/market_streams/__init__.py
deribit/sdk/market/market_streams/__init__.pyi
deribit/sdk/market/market_streams/_market_streams.py
deribit_trading_sdk-0.1.8.dist-info/METADATA
deribit_trading_sdk-0.1.8.dist-info/WHEEL
deribit_trading_sdk-0.1.8.dist-info/top_level.txt
deribit_trading_sdk-0.1.8.dist-info/RECORD
