Metadata-Version: 2.4
Name: deribit-trading-sdk
Version: 0.1.8
Summary: The unofficial Deribit API SDK, by Tribulnation. Compatible with Trading SDK.
Author-email: Marcel Claramunt <marcel@tribulnation.com>
Project-URL: repo, https://github.com/tribulnation/deribit.git
Requires-Python: >=3.10
Requires-Dist: lazy-loader
Requires-Dist: httpx
Requires-Dist: websockets
Requires-Dist: pydantic
Provides-Extra: sdk
Requires-Dist: trading-sdk; extra == "sdk"
Provides-Extra: orjson
Requires-Dist: orjson; extra == "orjson"
